Workbook

Sheet Scorecard
A1: Governance and Cost Review Scorecard - Pashun Sports multi-agent system
A2: Score each criterion from 0 to 5 (0 = nothing in place, 3 = partly in place, 5 = fully in place and tested). Weights must total 100. Yellow cells are inputs; scores shown are a worked example.
A4: Area | B4: Criterion | C4: Weight | D4: Score (0-5) | E4: Weighted score | F4: Status | G4: Owner | H4: Evidence / next action
A5: Architecture | B5: Each agent has one clear job and a routing description with a boundary statement | C5: 12 | D5: 4 | E5: =C5*D5/5 | F5: =IF(D5>=4,"Green",IF(D5>=3,"Amber","Red")) | G5: Paul Ashun | H5: Four agents have descriptions; the ambiguous "order is late" probe fixed by tightening descriptions
A6: Architecture | B6: Front door holds no deep domain knowledge (routing plus fallback only) | C6: 5 | D6: 5 | E6: =C6*D6/5 | F6: =IF(D6>=4,"Green",IF(D6>=3,"Amber","Red")) | G6: Paul Ashun | H6: Front door stripped back to routing plus fallback
A7: Knowledge | B7: Each specialist has only the knowledge it needs; sources are approved | C7: 8 | D7: 4 | E7: =C7*D7/5 | F7: =IF(D7>=4,"Green",IF(D7>=3,"Amber","Red")) | G7: Jamie Jordan | H7: Customer Policies, Ridgeline agreement and sales workbook only
A8: Security | B8: DLP policy with Business / Non-Business / Blocked applied to Production | C8: 10 | D8: 4 | E8: =C8*D8/5 | F8: =IF(D8>=4,"Green",IF(D8>=3,"Amber","Red")) | G8: Paul Ashun | H8: DLP applied; confirm Production scope
A9: Security | B9: Sharing restricted to an Entra security group (PS-All-Employees); Authenticate with Microsoft | C9: 10 | D9: 5 | E9: =C9*D9/5 | F9: =IF(D9>=4,"Green",IF(D9>=3,"Amber","Red")) | G9: Paul Ashun | H9: PS-All-Employees group set; Authenticate with Microsoft on all four
A10: Security | B10: Wholesale prices and other restricted data cannot be reached (tested) | C10: 8 | D10: 5 | E10: =C10*D10/5 | F10: =IF(D10>=4,"Green",IF(D10>=3,"Amber","Red")) | G10: Morgan Reyes | H10: Wholesale price probe refused and logged
A11: Lifecycle | B11: Solution-based promotion Dev > Test > Production; tests rerun in Test | C11: 14 | D11: 4 | E11: =C11*D11/5 | F11: =IF(D11>=4,"Green",IF(D11>=3,"Amber","Red")) | G11: Jamie Jordan | H11: Solution exported Dev to Test; Production import pending
A12: Cost | B12: Forecast built in the Agent Usage Estimator with 30% contingency and a worst case | C12: 10 | D12: 4 | E12: =C12*D12/5 | F12: =IF(D12>=4,"Green",IF(D12>=3,"Amber","Red")) | G12: Morgan Reyes | H12: Estimator done; worst case still to add
A13: Cost | B13: Forecast compared with the Capacity page; billing alert at 80% | C13: 9 | D13: 3 | E13: =C13*D13/5 | F13: =IF(D13>=4,"Green",IF(D13>=3,"Amber","Red")) | G13: Morgan Reyes | H13: Capacity page checked once; alert not set yet
A14: Operations | B14: Monthly review scheduled with an owner per agent | C14: 9 | D14: 3 | E14: =C14*D14/5 | F14: =IF(D14>=4,"Green",IF(D14>=3,"Amber","Red")) | G14: Jamie Jordan | H14: First review booked, owners to confirm
A15: Operations | B15: Monitor metrics tracked: engagement, resolution, escalation, abandoned sessions | C15: 5 | D15: 3 | E15: =C15*D15/5 | F15: =IF(D15>=4,"Green",IF(D15>=3,"Amber","Red")) | G15: Jamie Jordan | H15: Monitor tab opened; no baseline yet
A16: Totals | C16: =SUM(C5:C15) | E16: =SUM(E5:E15)
A17: Weights total check | C17: =IF(C16=100,"OK: weights total 100","Fix: weights must total 100")
A18: Overall score (%) | C18: =E16/C16
A19: Rating | C19: =IF(C18>=0.85,"Ready for scale",IF(C18>=0.7,"Ready for pilot with actions",IF(C18>=0.5,"Not ready: close the red items","Stop: major gaps")))
A20: Red items | C20: =COUNTIF(F5:F15,"Red")
A21: Amber items | C21: =COUNTIF(F5:F15,"Amber")
A22: Weighted score by area (see Area Summary sheet)

Sheet Area Summary
A1: Area | B1: Weight | C1: Weighted score | D1: Area score (%) | E1: Status
A2: Architecture | B2: =SUMIFS(Scorecard!$C$5:$C$15,Scorecard!$A$5:$A$15,A2) | C2: =SUMIFS(Scorecard!$E$5:$E$15,Scorecard!$A$5:$A$15,A2) | D2: =IF(B2=0,"",C2/B2) | E2: =IF(D2="","",IF(D2>=0.8,"Green",IF(D2>=0.6,"Amber","Red")))
A3: Knowledge | B3: =SUMIFS(Scorecard!$C$5:$C$15,Scorecard!$A$5:$A$15,A3) | C3: =SUMIFS(Scorecard!$E$5:$E$15,Scorecard!$A$5:$A$15,A3) | D3: =IF(B3=0,"",C3/B3) | E3: =IF(D3="","",IF(D3>=0.8,"Green",IF(D3>=0.6,"Amber","Red")))
A4: Security | B4: =SUMIFS(Scorecard!$C$5:$C$15,Scorecard!$A$5:$A$15,A4) | C4: =SUMIFS(Scorecard!$E$5:$E$15,Scorecard!$A$5:$A$15,A4) | D4: =IF(B4=0,"",C4/B4) | E4: =IF(D4="","",IF(D4>=0.8,"Green",IF(D4>=0.6,"Amber","Red")))
A5: Lifecycle | B5: =SUMIFS(Scorecard!$C$5:$C$15,Scorecard!$A$5:$A$15,A5) | C5: =SUMIFS(Scorecard!$E$5:$E$15,Scorecard!$A$5:$A$15,A5) | D5: =IF(B5=0,"",C5/B5) | E5: =IF(D5="","",IF(D5>=0.8,"Green",IF(D5>=0.6,"Amber","Red")))
A6: Cost | B6: =SUMIFS(Scorecard!$C$5:$C$15,Scorecard!$A$5:$A$15,A6) | C6: =SUMIFS(Scorecard!$E$5:$E$15,Scorecard!$A$5:$A$15,A6) | D6: =IF(B6=0,"",C6/B6) | E6: =IF(D6="","",IF(D6>=0.8,"Green",IF(D6>=0.6,"Amber","Red")))
A7: Operations | B7: =SUMIFS(Scorecard!$C$5:$C$15,Scorecard!$A$5:$A$15,A7) | C7: =SUMIFS(Scorecard!$E$5:$E$15,Scorecard!$A$5:$A$15,A7) | D7: =IF(B7=0,"",C7/B7) | E7: =IF(D7="","",IF(D7>=0.8,"Green",IF(D7>=0.6,"Amber","Red")))

Sheet Monthly Agent Review
A1: Agent | B1: Owner | C1: Engagement rate | D1: Resolution rate | E1: Escalation rate | F1: Abandoned sessions rate | G1: Target escalation rate (max) | H1: Target resolution rate (min) | I1: Escalation check | J1: Resolution check | K1: Top 3 improvements | L1: Credits used this month | M1: Credits forecast | N1: Credit variance
A2: PS-Project-Support-Helper | B2: Jamie Jordan | G2: 0.12 | H2: 0.7 | I2: =IF(E2="","",IF(E2<=G2,"OK","Above target")) | J2: =IF(D2="","",IF(D2>=H2,"OK","Below target")) | N2: =IF(OR(L2="",M2=""),"",L2-M2)
A3: PS-Customer-Service | B3: Jamie Jordan | G3: 0.12 | H3: 0.7 | I3: =IF(E3="","",IF(E3<=G3,"OK","Above target")) | J3: =IF(D3="","",IF(D3>=H3,"OK","Below target")) | N3: =IF(OR(L3="",M3=""),"",L3-M3)
A4: PS-Supplier-Follow-Up | B4: Jamie Jordan | G4: 0.12 | H4: 0.7 | I4: =IF(E4="","",IF(E4<=G4,"OK","Above target")) | J4: =IF(D4="","",IF(D4>=H4,"OK","Below target")) | N4: =IF(OR(L4="",M4=""),"",L4-M4)
A5: PS-Sales-Reporter | B5: Morgan Reyes | G5: 0.12 | H5: 0.7 | I5: =IF(E5="","",IF(E5<=G5,"OK","Above target")) | J5: =IF(D5="","",IF(D5>=H5,"OK","Below target")) | N5: =IF(OR(L5="",M5=""),"",L5-M5)
A7: Enter last month's figures from the Monitor tab (engagement, resolution, escalation, abandoned sessions) and credit use from the Capacity page. Targets are starting points: agree your own with each owner. Targets of 12% escalation and 70% resolution are examples only.

Sheet Top 3 Governance Gaps
A1: Gap | B1: Area (DLP / ownership / sharing scope / other) | C1: Why it matters | D1: Owner (named person) | E1: Fix by | F1: Status
A2: Example: Production DLP policy not yet reviewed after Operations Agent added | B2: DLP | C2: A new connector could mix Business and Non-Business groups | D2: Paul Ashun | E2: Nov 30, 2026 | F2: Open
